spinex_clustering/__init__.py
spinex_clustering/clustering.py
spinex_clustering-0.0.1.dist-info/LICENSE.py
spinex_clustering-0.0.1.dist-info/METADATA
spinex_clustering-0.0.1.dist-info/WHEEL
spinex_clustering-0.0.1.dist-info/top_level.txt
spinex_clustering-0.0.1.dist-info/RECORD
