Metadata-Version: 2.1
Name: spinex_clustering
Version: 0.0.1
Summary: An advanced clustering algorithm with multi-level analysis capabilities
Home-page: https://https://github.com/mznaser-clemson
Author: M.Z. Naser and A.Z. Naser
Author-email: mznaser@clemson.edu
Classifier: Programming Language :: Python :: 3
Classifier: Programming Language :: Python :: 3.7
Classifier: Programming Language :: Python :: 3.8
Classifier: Programming Language :: Python :: 3.9
Classifier: License :: OSI Approved :: MIT License
Classifier: Operating System :: OS Independent
Classifier: Topic :: Scientific/Engineering :: Artificial Intelligence
Classifier: Topic :: Scientific/Engineering :: Information Analysis
Requires-Python: >=3.7
License-File: LICENSE.py
Requires-Dist: numpy>=1.19.0
Requires-Dist: scipy>=1.6.0
Requires-Dist: scikit-learn>=0.24.0
Requires-Dist: numba>=0.53.0
Requires-Dist: umap-learn>=0.5.0
